auto_click_auto/__init__.py
auto_click_auto/constants.py
auto_click_auto/core.py
auto_click_auto/exceptions.py
auto_click_auto/py.typed
auto_click_auto/utils.py
auto_click_auto-0.1.5.dist-info/LICENSE
auto_click_auto-0.1.5.dist-info/METADATA
auto_click_auto-0.1.5.dist-info/WHEEL
auto_click_auto-0.1.5.dist-info/RECORD
