Metadata-Version: 2.1
Name: auto-click-auto
Version: 0.1.5
Summary: Automatically enable tab autocompletion for shells in Click CLI applications.
Home-page: https://github.com/KAUTH/auto-click-auto
License: MIT
Keywords: click,autocomplete,shell
Author: Konstantinos Papadopoulos
Author-email: konpap1996@yahoo.com
Maintainer: Konstantinos Papadopoulos
Maintainer-email: konpap1996@yahoo.com
Requires-Python: >=3.7,<4.0
Classifier: License :: OSI Approved :: MIT License
Classifier: Natural Language :: English
Classifier: Operating System :: OS Independent
Classifier: Programming Language :: Python
Classifier: Programming Language :: Python :: 3
Classifier: Programming Language :: Python :: 3.7
Classifier: Programming Language :: Python :: 3.8
Classifier: Programming Language :: Python :: 3.9
Classifier: Programming Language :: Python :: 3.10
Classifier: Programming Language :: Python :: 3.11
Classifier: Programming Language :: Python :: 3.12
Classifier: Programming Language :: Python :: 3.11 
Classifier: Programming Language :: Python :: Implementation :: PyPy
Classifier: Topic :: Software Development
Requires-Dist: click (>=8.1.4,<9.0.0)
Project-URL: Documentation, https://github.com/KAUTH/auto-click-auto/blob/main/README.md
Project-URL: Repository, https://github.com/KAUTH/auto-click-auto
